llama_index_spanner/__init__.py
llama_index_spanner/graph_retriever.py
llama_index_spanner/graph_utils.py
llama_index_spanner/prompts.py
llama_index_spanner/property_graph_store.py
llama_index_spanner/schema.py
llama_index_spanner/spanner.py
llama_index_spanner/type_utils.py
llama_index_spanner/version.py
llama_index_spanner-0.1.5.dist-info/licenses/LICENSE
llama_index_spanner-0.1.5.dist-info/METADATA
llama_index_spanner-0.1.5.dist-info/WHEEL
llama_index_spanner-0.1.5.dist-info/top_level.txt
llama_index_spanner-0.1.5.dist-info/RECORD
