Metadata-Version: 2.4
Name: llama-index-spanner
Version: 0.1.5
Summary: LlamaIndex integrations for Google Cloud Spanner
Author-email: Google LLC <googleapis-packages@google.com>
License: 
Project-URL: Homepage, https://github.com/googleapis/llama-index-spanner-python
Project-URL: Repository, https://github.com/googleapis/llama-index-spanner-python.git
Project-URL: Bug Tracker, https://github.com/googleapis/llama-index-spanner-python/issues
Project-URL: Changelog, https://github.com/googleapis/llama-index-spanner-python/blob/main/CHANGELOG.md
Classifier: Intended Audience :: Developers
Classifier: License :: OSI Approved :: Apache Software License
Classifier: Programming Language :: Python
Classifier: Programming Language :: Python :: 3
Classifier: Programming Language :: Python :: 3.9
Classifier: Programming Language :: Python :: 3.10
Classifier: Programming Language :: Python :: 3.11
Classifier: Programming Language :: Python :: 3.12
Requires-Python: <4.0,>=3.9
License-File: LICENSE
Requires-Dist: google-cloud-spanner<4.0.0,>=3.41.0
Requires-Dist: llama-index-core<1.0.0,>=0.12.48
Requires-Dist: llama-index<1.0.0,>=0.12.41
Provides-Extra: lint
Requires-Dist: black[jupyter]==25.1.0; extra == "lint"
Requires-Dist: flake8==6.1.0; extra == "lint"
Requires-Dist: isort==5.13.2; extra == "lint"
Provides-Extra: test
Requires-Dist: black[jupyter]==25.1.0; extra == "test"
Requires-Dist: flake8==6.1.0; extra == "test"
Requires-Dist: isort==5.13.2; extra == "test"
Requires-Dist: mypy==1.16.0; extra == "test"
Requires-Dist: pytest==8.3.3; extra == "test"
Requires-Dist: pytest-retry==1.7.0; extra == "test"
Requires-Dist: pytest-xdist==3.6.1; extra == "test"
Requires-Dist: pytest-cov==5.0.0; extra == "test"
Requires-Dist: pytest-asyncio==0.24.0; extra == "test"
Requires-Dist: llama-index-readers-wikipedia==0.4.1; extra == "test"
Requires-Dist: llama-index-embeddings-google-genai==0.3.1; extra == "test"
Requires-Dist: llama-index-llms-google-genai==0.6.2; extra == "test"
Requires-Dist: google-genai==1.31.0; extra == "test"
Requires-Dist: wikipedia==1.4.0; extra == "test"
Requires-Dist: ipykernel==6.29.5; extra == "test"
Dynamic: license-file
